odoo/addons/sale_tier_validation/README.rst
odoo/addons/sale_tier_validation/__init__.py
odoo/addons/sale_tier_validation/__manifest__.py
odoo/addons/sale_tier_validation/data/mail_data.xml
odoo/addons/sale_tier_validation/i18n/es.po
odoo/addons/sale_tier_validation/i18n/sale_tier_validation.pot
odoo/addons/sale_tier_validation/i18n/sv.po
odoo/addons/sale_tier_validation/i18n/zh_CN.po
odoo/addons/sale_tier_validation/models/__init__.py
odoo/addons/sale_tier_validation/models/sale_order.py
odoo/addons/sale_tier_validation/models/tier_definition.py
odoo/addons/sale_tier_validation/readme/CONFIGURE.rst
odoo/addons/sale_tier_validation/readme/CONTRIBUTORS.rst
odoo/addons/sale_tier_validation/readme/DESCRIPTION.rst
odoo/addons/sale_tier_validation/readme/INSTALL.rst
odoo/addons/sale_tier_validation/readme/USAGE.rst
odoo/addons/sale_tier_validation/static/description/icon.png
odoo/addons/sale_tier_validation/static/description/index.html
odoo/addons/sale_tier_validation/tests/__init__.py
odoo/addons/sale_tier_validation/tests/test_tier_validation.py
odoo/addons/sale_tier_validation/views/sale_order_view.xml
odoo14_addon_sale_tier_validation-14.0.1.1.0.dist-info/METADATA
odoo14_addon_sale_tier_validation-14.0.1.1.0.dist-info/WHEEL
odoo14_addon_sale_tier_validation-14.0.1.1.0.dist-info/top_level.txt
odoo14_addon_sale_tier_validation-14.0.1.1.0.dist-info/RECORD
